promptmachine_eval/__init__.py
promptmachine_eval/battle.py
promptmachine_eval/cli.py
promptmachine_eval/cost.py
promptmachine_eval/elo.py
promptmachine_eval/matchmaking.py
promptmachine_eval/runner.py
promptmachine_eval/arena/__init__.py
promptmachine_eval/benchmarks/__init__.py
promptmachine_eval/benchmarks/base.py
promptmachine_eval/reporters/__init__.py
promptmachine_eval/reporters/base.py
promptmachine_eval/reporters/markdown.py
promptmachine_eval-0.1.0.dist-info/METADATA
promptmachine_eval-0.1.0.dist-info/WHEEL
promptmachine_eval-0.1.0.dist-info/entry_points.txt
promptmachine_eval-0.1.0.dist-info/licenses/LICENSE
promptmachine_eval-0.1.0.dist-info/RECORD
