Metadata-Version: 2.4
Name: promptmachine-eval
Version: 0.1.0
Summary: LLM evaluation framework with ELO ratings, arena battles, and benchmark testing
Project-URL: Homepage, https://github.com/manicinc/promptmachine
Project-URL: Documentation, https://manicinc.github.io/promptmachine
Project-URL: Repository, https://github.com/manicinc/promptmachine
Project-URL: Issues, https://github.com/manicinc/promptmachine/issues
Project-URL: Changelog, https://github.com/manicinc/promptmachine/blob/main/packages/promptmachine-eval/CHANGELOG.md
Author-email: Manic Inc <team@manic.agency>
Maintainer-email: Johnny Dunn <johnnyfived@protonmail.com>
License-Expression: MIT
License-File: LICENSE
Keywords: ai,arena,benchmark,claude,elo,evaluation,gpt,llm,prompt,testing
Classifier: Development Status :: 4 - Beta
Classifier: Environment :: Console
Classifier: Intended Audience :: Developers
Classifier: Intended Audience :: Science/Research
Classifier: License :: OSI Approved :: MIT License
Classifier: Operating System :: OS Independent
Classifier: Programming Language :: Python :: 3
Classifier: Programming Language :: Python :: 3.9
Classifier: Programming Language :: Python :: 3.10
Classifier: Programming Language :: Python :: 3.11
Classifier: Programming Language :: Python :: 3.12
Classifier: Topic :: Scientific/Engineering :: Artificial Intelligence
Classifier: Topic :: Software Development :: Testing
Classifier: Typing :: Typed
Requires-Python: >=3.9
Requires-Dist: anthropic>=0.7.0
Requires-Dist: httpx>=0.25.0
Requires-Dist: openai>=1.3.0
Requires-Dist: pydantic-settings>=2.0.0
Requires-Dist: pydantic>=2.0.0
Requires-Dist: python-dotenv>=1.0.0
Requires-Dist: pyyaml>=6.0.0
Requires-Dist: rich>=13.0.0
Requires-Dist: structlog>=23.2.0
Requires-Dist: tenacity>=8.2.0
Requires-Dist: typer>=0.9.0
Provides-Extra: all
Requires-Dist: black>=23.0.0; extra == 'all'
Requires-Dist: jupyter>=1.0.0; extra == 'all'
Requires-Dist: matplotlib>=3.7.0; extra == 'all'
Requires-Dist: mypy>=1.7.0; extra == 'all'
Requires-Dist: pandas>=2.0.0; extra == 'all'
Requires-Dist: pre-commit>=3.5.0; extra == 'all'
Requires-Dist: pytest-asyncio>=0.21.0; extra == 'all'
Requires-Dist: pytest-cov>=4.1.0; extra == 'all'
Requires-Dist: pytest>=7.4.0; extra == 'all'
Requires-Dist: ruff>=0.1.0; extra == 'all'
Provides-Extra: dev
Requires-Dist: black>=23.0.0; extra == 'dev'
Requires-Dist: mypy>=1.7.0; extra == 'dev'
Requires-Dist: pre-commit>=3.5.0; extra == 'dev'
Requires-Dist: pytest-asyncio>=0.21.0; extra == 'dev'
Requires-Dist: pytest-cov>=4.1.0; extra == 'dev'
Requires-Dist: pytest>=7.4.0; extra == 'dev'
Requires-Dist: ruff>=0.1.0; extra == 'dev'
Provides-Extra: notebooks
Requires-Dist: jupyter>=1.0.0; extra == 'notebooks'
Requires-Dist: matplotlib>=3.7.0; extra == 'notebooks'
Requires-Dist: pandas>=2.0.0; extra == 'notebooks'
